{
  "id": "noble-conspiracy",
  "name": "Noble Conspiracy",
  "tier": "MAJOR",
  "description": "Nobles plot to overthrow the kingdom's leadership",
  "percentileMin": 53,
  "percentileMax": 59,
  "skillOptions": [
    {
      "skill": "stealth",
      "description": "uncover plot",
      "successEffect": "Conspiracy exposed and dealt with, no effect",
      "failureEffect": "Lose 1d4 Gold, -1 fame",
      "criticalFailureEffect": "Lose 2d4 Gold, -1 fame, one random PC loses kingdom action this turn, +1 unrest"
    },
    {
      "skill": "intimidation",
      "description": "arrests",
      "successEffect": "Conspiracy exposed and dealt with, no effect",
      "failureEffect": "Lose 1d4 Gold, -1 fame",
      "criticalFailureEffect": "Lose 2d4 Gold, -1 fame, one random PC loses kingdom action this turn, +1 unrest"
    },
    {
      "skill": "society",
      "description": "political maneuvering",
      "successEffect": "Conspiracy exposed and dealt with, no effect",
      "failureEffect": "Lose 1d4 Gold, -1 fame",
      "criticalFailureEffect": "Lose 2d4 Gold, -1 fame, one random PC loses kingdom action this turn, +1 unrest"
    },
    {
      "skill": "occultism",
      "description": "divine truth",
      "successEffect": "Conspiracy exposed and dealt with, no effect",
      "failureEffect": "Lose 1d4 Gold, -1 fame",
      "criticalFailureEffect": "Lose 2d4 Gold, -1 fame, one random PC loses kingdom action this turn, +1 unrest"
    }
  ]
}