{
  "id": "rebellion-trade-embargo",
  "name": "Trade Embargo",
  "tier": "MAJOR",
  "description": "A complete trade embargo devastates your economy",
  "skills": [
    {
      "skill": "diplomacy",
      "description": "negotiate"
    },
    {
      "skill": "society",
      "description": "find loopholes"
    },
    {
      "skill": "deception",
      "description": "smuggling routes"
    },
    {
      "skill": "arcana",
      "description": "teleportation network"
    }
  ],
  "effects": {
    "success": {
      "msg": "Trade continues, no effect",
      "modifiers": []
    },
    "failure": {
      "msg": "Lose 2d4 Gold OR 2d4+1 Resources (player's choice)",
      "modifiers": []
    },
    "criticalFailure": {
      "msg": "Lose 3d4 Gold AND 2d4+1 Resources, +1 Unrest",
      "modifiers": []
    }
  }
}