{
  "id": "festive-invitation",
  "name": "Festive Invitation",
  "description": "A neighboring kingdom invites your leaders to a grand festival.",
  "traits": [
    "beneficial"
  ],
  "location": "",
  "modifier": 0,
  "resolvedOn": [
    "criticalSuccess",
    "success"
  ],
  "special": "If you bring at least 1 Resource as a gift, gain +2 to the check.",
  "ifUnresolved": {
    "type": "expires",
    "expires": {
      "message": "Festive Invitation expires"
    }
  },
  "skills": [
    {
      "skill": "diplomacy",
      "description": "formal attendance"
    },
    {
      "skill": "performance",
      "description": "entertain hosts"
    },
    {
      "skill": "society",
      "description": "navigate customs"
    }
  ],
  "effects": {
    "criticalSuccess": {
      "msg": "Great success; Gold equal to Resources brought +1, -1 Unrest",
      "modifiers": [
        {
          "type": "untyped",
          "name": "Great success",
          "value": 1,
          "selector": "gold",
          "enabled": true,
          "turns": 1
        },
        {
          "type": "untyped",
          "name": "Great success",
          "value": -1,
          "selector": "unrest",
          "enabled": true
        }
      ]
    },
    "success": {
      "msg": "Pleasant visit; Gold equal to Resources brought",
      "modifiers": [
        {
          "type": "untyped",
          "name": "Pleasant visit",
          "value": 1,
          "selector": "gold",
          "enabled": true,
          "turns": 1
        }
      ]
    },
    "failure": {
      "msg": "Adequate visit; gifts not reciprocated",
      "modifiers": []
    },
    "criticalFailure": {
      "msg": "Diplomatic faux pas; +1 Unrest",
      "modifiers": [
        {
          "type": "untyped",
          "name": "Diplomatic faux pas",
          "value": 1,
          "selector": "unrest",
          "enabled": true
        }
      ]
    }
  }
}
