{
  "id": "plague",
  "name": "Plague",
  "description": "Disease spreads rapidly through your settlements.",
  "traits": [
    "dangerous",
    "continuous"
  ],
  "location": "Largest settlement, then spreads",
  "modifier": 0,
  "resolvedOn": [
    "criticalSuccess",
    "success"
  ],
  "special": "Settlements with Medicine & Healing or Faith & Nature structures gain an untyped bonus equal to the tier to checks. Bonuses from different structure types stack.",
  "ifUnresolved": {
    "type": "continuous",
    "continuous": {
      "becomesModifier": true,
      "modifierTemplate": {
        "name": "Plague Outbreak",
        "description": "Disease continues to spread through your settlements, weakening the population",
        "duration": "until-resolved",
        "severity": "critical",
        "icon": "fas fa-virus",
        "priority": 90,
        "effects": {
          "unrest": 1,
          "gold": -2,
          "food": -1
        },
        "resolution": {
          "skills": [
            "medicine",
            "religion",
            "society"
          ],
          "dc": 18,
          "automatic": {
            "condition": "build:temple,hospital",
            "description": "Build a temple or hospital to provide healing"
          },
          "onResolution": {
            "successMsg": "The plague has been contained and the sick are recovering!",
            "failureMsg": "The plague continues to ravage your settlements despite your efforts"
          }
        },
        "escalation": {
          "turnsUntilEscalation": 2,
          "escalatedModifier": {
            "name": "Devastating Pandemic",
            "description": "The plague has become a full pandemic, causing mass casualties",
            "severity": "critical",
            "effects": {
              "unrest": 2,
              "gold": -4,
              "food": -2
            },
            "resolution": {
              "dc": 22
            }
          }
        }
      }
    }
  },
  "skills": [
    {
      "skill": "medicine",
      "description": "treat the sick"
    },
    {
      "skill": "religion",
      "description": "divine healing"
    },
    {
      "skill": "society",
      "description": "quarantine measures"
    }
  ],
  "effects": {
    "criticalSuccess": {
      "msg": "Plague cured; -1 Unrest, **event ends**",
      "modifiers": [
        {
          "type": "untyped",
          "name": "Plague cured",
          "value": -1,
          "selector": "unrest",
          "enabled": true
        }
      ]
    },
    "success": {
      "msg": "Plague contained; **event ends**",
      "modifiers": []
    },
    "failure": {
      "msg": "Plague spreads; +1 Unrest, -2 Gold, spreads to a settlement connected by a road",
      "modifiers": [
        {
          "type": "untyped",
          "name": "Plague spreads",
          "value": 1,
          "selector": "unrest",
          "enabled": true
        },
        {
          "type": "untyped",
          "name": "Plague spreads",
          "value": -2,
          "selector": "gold",
          "enabled": true,
          "turns": 1
        }
      ]
    },
    "criticalFailure": {
      "msg": "Devastating outbreak; +2 Unrest, -2 Gold, spreads to all settlements connected by a road",
      "modifiers": [
        {
          "type": "untyped",
          "name": "Devastating outbreak",
          "value": 2,
          "selector": "unrest",
          "enabled": true
        },
        {
          "type": "untyped",
          "name": "Devastating outbreak",
          "value": -2,
          "selector": "gold",
          "enabled": true,
          "turns": 1
        }
      ]
    }
  }
}
