{
  "id": "recruit-unit",
  "name": "Recruit Army",
  "category": "military-operations",
  "brief": "Raise new troops for your armies",
  "description": "Rally citizens to arms, drawing from the population to form new military units through inspiration, coercion, or demonstration of prowess",
  "skills": [
    {
      "skill": "diplomacy",
      "description": "inspire patriotism"
    },
    {
      "skill": "intimidation",
      "description": "conscription"
    },
    {
      "skill": "society",
      "description": "civic duty"
    },
    {
      "skill": "performance",
      "description": "recruitment rallies"
    },
    {
      "skill": "athletics",
      "description": "demonstrations of prowess"
    }
  ],
  "outcomes": {
    "criticalSuccess": {
      "description": "Patriotic fervor spreads.",
      "modifiers": [
        {
          "type": "static",
          "resource": "unrest",
          "value": -1,
          "duration": "immediate"
        }
      ],
      "gameCommands": [
        {
          "type": "recruitArmy",
          "level": "kingdom-level",
          "description": "Create new army unit at party level"
        }
      ]
    },
    "success": {
      "description": "Troops are recruited.",
      "modifiers": [],
      "gameCommands": [
        {
          "type": "recruitArmy",
          "level": "kingdom-level",
          "description": "Create new army unit at party level"
        }
      ]
    },
    "failure": {
      "description": "Recruitment fails.",
      "modifiers": [],
      "gameCommands": []
    },
    "criticalFailure": {
      "description": "The recruitment attempt angers the populace.",
      "modifiers": [
        {
          "type": "static",
          "resource": "unrest",
          "value": 1,
          "duration": "immediate"
        }
      ],
      "gameCommands": []
    }
  },
  "failureCausesUnrest": true
}
